AUTHORS.txt
CHANCES.txt
LICENSE.txt
MANIFEST.in
README.rst
setup.py
docs/installing.rst
docs/scripts/laptop-pm.rst
laptop_pm/__init__.py
laptop_pm/__version__.py
laptop_pm.egg-info/PKG-INFO
laptop_pm.egg-info/SOURCES.txt
laptop_pm.egg-info/dependency_links.txt
laptop_pm.egg-info/not-zip-safe
laptop_pm.egg-info/top_level.txt
scripts/laptop-pm