Metadata-Version: 1.1
Name: laptop-pm
Version: 0.0.3.18
Summary: Python powermanagement script for my linux laptop.
Home-page: http://bitbucket.org/igraltist/laptop-pm
Author: Jens Kasten
Author-email: jens@kasten-edv.de
License: GNU GPLv3
Keywords: laptop powersave
Platform: UNKNOWN
Classifier: Development Status :: 4 - Beta
Classifier: Intended Audience :: System Administrators
Classifier: License :: OSI Approved :: GNU General Public License v3 (GPLv3)
Classifier: Operating System :: POSIX :: Linux
Classifier: Programming Language :: Python :: 3.4
Classifier: Topic :: System :: Systems Administration
